pstree_json/__init__.py
pstree_json/main.py
pstree_json-1.0.0.dist-info/METADATA
pstree_json-1.0.0.dist-info/WHEEL
pstree_json-1.0.0.dist-info/entry_points.txt
pstree_json-1.0.0.dist-info/top_level.txt
pstree_json-1.0.0.dist-info/RECORD
