Metadata-Version: 2.4
Name: pstree-json
Version: 1.0.0
Summary: Output the process tree in machine-readable JSON.
Author-email: Author <talwrii@gmail.com>
License: MIT
Keywords: pstree,process,tree,sysadmin,JSON
Requires-Python: >=3.7
Requires-Dist: psutil
